odoo8_addon_mgmtsystem-8.0.1.0.0.99.dev12-nspkg.pth
odoo_addons/mgmtsystem/__init__.py
odoo_addons/mgmtsystem/__openerp__.py
odoo_addons/mgmtsystem/board_mgmtsystem_view.xml
odoo_addons/mgmtsystem/menus.xml
odoo_addons/mgmtsystem/mgmtsystem_system.py
odoo_addons/mgmtsystem/mgmtsystem_system.xml
odoo_addons/mgmtsystem/i18n/de.po
odoo_addons/mgmtsystem/i18n/es.po
odoo_addons/mgmtsystem/i18n/fi.po
odoo_addons/mgmtsystem/i18n/fr.po
odoo_addons/mgmtsystem/i18n/hr.po
odoo_addons/mgmtsystem/i18n/hu.po
odoo_addons/mgmtsystem/i18n/id.po
odoo_addons/mgmtsystem/i18n/lv.po
odoo_addons/mgmtsystem/i18n/mgmtsystem.pot
odoo_addons/mgmtsystem/i18n/nb.po
odoo_addons/mgmtsystem/i18n/nn.po
odoo_addons/mgmtsystem/i18n/pl.po
odoo_addons/mgmtsystem/i18n/pt.po
odoo_addons/mgmtsystem/i18n/pt_BR.po
odoo_addons/mgmtsystem/i18n/sl.po
odoo_addons/mgmtsystem/i18n/sv.po
odoo_addons/mgmtsystem/i18n/th.po
odoo_addons/mgmtsystem/i18n/tr.po
odoo_addons/mgmtsystem/i18n/vi.po
odoo_addons/mgmtsystem/i18n/zh_CN.po
odoo_addons/mgmtsystem/images/mgmtsystem-hover.png
odoo_addons/mgmtsystem/images/mgmtsystem.png
odoo_addons/mgmtsystem/migrations/6.1.1.0/openupgrade_analysis.txt
odoo_addons/mgmtsystem/security/ir.model.access.csv
odoo_addons/mgmtsystem/security/mgmtsystem_security.xml
odoo_addons/mgmtsystem/static/description/icon.png
odoo_addons/mgmtsystem/tests/__init__.py
odoo_addons/mgmtsystem/tests/test_create_mgmtsystem.py
odoo8_addon_mgmtsystem-8.0.1.0.0.99.dev12.dist-info/METADATA
odoo8_addon_mgmtsystem-8.0.1.0.0.99.dev12.dist-info/WHEEL
odoo8_addon_mgmtsystem-8.0.1.0.0.99.dev12.dist-info/namespace_packages.txt
odoo8_addon_mgmtsystem-8.0.1.0.0.99.dev12.dist-info/top_level.txt
odoo8_addon_mgmtsystem-8.0.1.0.0.99.dev12.dist-info/RECORD
